<?xml version="1.0" encoding="UTF-8"?>
<FUNC AutoGen-Parameter-Version="1.0">
    <SCREEN>
        <JSPFILE>std_CHG_Rule.jsp</JSPFILE>
    </SCREEN>
    <DOSCREEN ISDEF="T"/>
    <FUNCTION>
        <MODULE TYPE="STD">STAN</MODULE>
        <MODULE_DESC>Standing Data</MODULE_DESC>
        <EVENT>STAN_Charge_Pending</EVENT>
        <ID>M8qtffh77CQG</ID>
        <NAME>ChgCommAgreementAdd2Pending</NAME>
        <DESC>Agreement Add to Pending</DESC>
        <FUNSHORTNAME>CommAgreeAdd_P</FUNSHORTNAME>
        <FUNCPROCEVENT></FUNCPROCEVENT>
        <LOCKCHECK>Y</LOCKCHECK>
        <HOLDMASTER>T</HOLDMASTER>
        <FUNCTYPE>GE</FUNCTYPE>
        <MAINCOMP name="STD Manager">STDManager</MAINCOMP>
        <UIStyle>C</UIStyle>
        <ADDMASTER>N</ADDMASTER>
        <ATTR_ID name="ChgCommAgreementAdd2Pending">M8qtffh77CQG</ATTR_ID>
        <CATALOGID></CATALOGID>
        <InSWIFT></InSWIFT>
        <GAPI></GAPI>
        <TransferTo></TransferTo>
        <OutSWIFT></OutSWIFT>
        <AUTO_RE_ID></AUTO_RE_ID>
    </FUNCTION>
</FUNC>