{
  "smtp": {
    "host": "smtp.gmail.com",
    "port": "587",
    "auth": "true",
    "starttls": "true",
    "protocols": "TLSv1.2",
    "user": "venumech049@gmail.com",
    "pass": "nciuydcwskxhcfwe"
  },
  "mail": {
    "subject": "Payables_Finance_Program_Application_Rejected",
    "from": "noreply@csbank.com",
    "body": "Dear ${name},\n\nChina Systems, in partnership with CS Bank, has reviewed your Payables Finance Program onboarding application.\n\nYour application has been rejected for the following reason:\n\n${rejectReason}\n\nPlease click the following secure link to review and resubmit your application:\n\n${link}\n\nIMPORTANT: This link is time-bound and can only be used once for security purposes.\nIf the link has expired or you need assistance, please contact your anchor customer.\n\nBest regards,\nSCF Integration Team\nCS Bank Support"
  }
}
