{"ZW":"ZIMBABWE","ZM":"ZAMBIA","YE":"YEMEN","EH":"WESTERN SAHARA","WF":"WALLIS AND FUTUNA","VI":"VIRGIN ISLANDS, U.S.","VG":"VIRGIN ISLANDS, BRITISH","VN":"VIET NAM","VE":"VENEZUELA, BOLIVARIAN REPUBLIC OF","VU":"VANUATU","UZ":"UZBEKISTAN","UY":"URUGUAY","UM":"UNITED STATES MINOR OUTLYING ISLANDS","US":"UNITED STATES","GB":"UNITED KINGDOM","AE":"UNITED ARAB EMIRATES","UA":"UKRAINE","UG":"UGANDA","TV":"TUVALU","TC":"TURKS AND CAICOS ISLANDS","TM":"TURKMENISTAN","TR":"TURKEY","TN":"TUNISIA","TT":"TRINIDAD AND TOBAGO","TO":"TONGA","TK":"TOKELAU","TG":"TOGO","TL":"TIMOR-LESTE","TH":"THAILAND","TZ":"TANZANIA, UNITED REPUBLIC OF","TJ":"TAJIKISTAN","TW":"TAIWAN, PROVINCE OF CHINA","SY":"SYRIAN ARAB REPUBLIC","CH":"SWITZERLAND","SE":"SWEDEN","SZ":"SWAZILAND","SJ":"SVALBARD AND JAN MAYEN","SR":"SURINAME","SD":"SUDAN","LK":"SRI LANKA","ES":"SPAIN","GS":"SOUTH GEORGIA AND THE SOUTH SANDWICH ISLANDS","ZA":"SOUTH AFRICA","SO":"SOMALIA","SB":"SOLOMON ISLANDS","SI":"SLOVENIA","SK":"SLOVAKIA","SX":"SINT MAARTEN (DUTCH PART)","SG":"SINGAPORE","SL":"SIERRA LEONE","SC":"SEYCHELLES","RS":"SERBIA","SN":"SENEGAL","SA":"SAUDI ARABIA","ST":"SAO TOME AND PRINCIPE","SM":"SAN MARINO","WS":"SAMOA","VC":"SAINT VINCENT AND THE GRENADINES","PM":"SAINT PIERRE AND MIQUELON","MF":"SAINT MARTIN (FRENCH PART)","LC":"SAINT LUCIA","KN":"SAINT KITTS AND NEVIS","SH":"SAINT HELENA, ASCENSION AND TRISTAN DA CUNHA","BL":"SAINT BARTHÉLEMY","RW":"RWANDA","RU":"RUSSIAN FEDERATION","RO":"ROMANIA","RE":"RÉUNION","QA":"QATAR","PR":"PUERTO RICO","PT":"PORTUGAL","PL":"POLAND","PN":"PITCAIRN","PH":"PHILIPPINES","PE":"PERU","PY":"PARAGUAY","PG":"PAPUA NEW GUINEA","PA":"PANAMA","PS":"PALESTINIAN TERRITORY, OCCUPIED","PW":"PALAU","PK":"PAKISTAN","OM":"OMAN","NO":"NORWAY","MP":"NORTHERN MARIANA ISLANDS","NF":"NORFOLK ISLAND","NU":"NIUE","NG":"NIGERIA","NE":"NIGER","NI":"NICARAGUA","NZ":"NEW ZEALAND","NC":"NEW CALEDONIA","NL":"NETHERLANDS","NP":"NEPAL","NR":"NAURU","NA":"NAMIBIA","MM":"MYANMAR","MZ":"MOZAMBIQUE","MA":"MOROCCO","MS":"MONTSERRAT","ME":"MONTENEGRO","MN":"MONGOLIA","MC":"MONACO","MD":"MOLDOVA, REPUBLIC OF","FM":"MICRONESIA, FEDERATED STATES OF","MX":"MEXICO","YT":"MAYOTTE","MU":"MAURITIUS","MR":"MAURITANIA","MQ":"MARTINIQUE","MH":"MARSHALL ISLANDS","MT":"MALTA","ML":"MALI","MV":"MALDIVES","MY":"MALAYSIA","MW":"MALAWI","MG":"MADAGASCAR","MK":"MACEDONIA, THE FORMER YUGOSLAV REPUBLIC OF","MO":"MACAO","LU":"LUXEMBOURG","LT":"LITHUANIA","LI":"LIECHTENSTEIN","LY":"LIBYAN ARAB JAMAHIRIYA","LR":"LIBERIA","LS":"LESOTHO","LB":"LEBANON","LV":"LATVIA","LA":"LAO PEOPLE'S DEMOCRATIC REPUBLIC","KG":"KYRGYZSTAN","KW":"KUWAIT","KR":"KOREA, REPUBLIC OF","KP":"KOREA, DEMOCRATIC PEOPLE'S REPUBLIC OF","KI":"KIRIBATI","KE":"KENYA","KZ":"KAZAKHSTAN","JO":"JORDAN","JE":"JERSEY","JP":"JAPAN","JM":"JAMAICA","IT":"ITALY","IL":"ISRAEL","IM":"ISLE OF MAN","IE":"IRELAND","IQ":"IRAQ","IR":"IRAN, ISLAMIC REPUBLIC OF","ID":"INDONESIA","IN":"INDIA","IS":"ICELAND","HU":"HUNGARY","HK":"HONG KONG","HN":"HONDURAS","VA":"HOLY SEE (VATICAN CITY STATE)","HM":"HEARD ISLAND AND MCDONALD ISLANDS","HT":"HAITI","GY":"GUYANA","GW":"GUINEA-BISSAU","GN":"GUINEA","GG":"GUERNSEY","GT":"GUATEMALA","GU":"GUAM","GP":"GUADELOUPE","GD":"GRENADA","GL":"GREENLAND","GR":"GREECE","GI":"GIBRALTAR","GH":"GHANA","DE":"GERMANY","GE":"GEORGIA","GM":"GAMBIA","GA":"GABON","TF":"FRENCH SOUTHERN TERRITORIES","PF":"FRENCH POLYNESIA","GF":"FRENCH GUIANA","FR":"FRANCE","FI":"FINLAND","FJ":"FIJI","FO":"FAROE ISLANDS","FK":"FALKLAND ISLANDS (MALVINAS)","ET":"ETHIOPIA","EE":"ESTONIA","ER":"ERITREA","GQ":"EQUATORIAL GUINEA","SV":"EL SALVADOR","EG":"EGYPT","EC":"ECUADOR","DO":"DOMINICAN REPUBLIC","DM":"DOMINICA","DJ":"DJIBOUTI","DK":"DENMARK","CZ":"CZECH REPUBLIC","CY":"CYPRUS","CU":"CUBA","CW":"CURAÇAO","HR":"CROATIA","CI":"CôTE D'IVOIRE","CR":"COSTA RICA","CK":"COOK ISLANDS","CD":"CONGO, THE DEMOCRATIC REPUBLIC OF THE","CG":"CONGO","KM":"COMOROS","CO":"COLOMBIA","CC":"COCOS (KEELING) ISLANDS","CX":"CHRISTMAS ISLAND","CN":"CHINA","CL":"CHILE","TD":"CHAD","CF":"CENTRAL AFRICAN REPUBLIC","KY":"CAYMAN ISLANDS","CV":"CAPE VERDE","CA":"CANADA","CM":"CAMEROON","KH":"CAMBODIA","BI":"BURUNDI","BF":"BURKINA FASO","BG":"BULGARIA","BN":"BRUNEI DARUSSALAM","IO":"BRITISH INDIAN OCEAN TERRITORY","BR":"BRAZIL","BV":"BOUVET ISLAND","BW":"BOTSWANA","BA":"BOSNIA AND HERZEGOVINA","BQ":"BONAIRE, SINT EUSTATIUS AND SABA","BO":"BOLIVIA, PLURINATIONAL STATE OF","BT":"BHUTAN","BM":"BERMUDA","BJ":"BENIN","BZ":"BELIZE","BE":"BELGIUM","BY":"BELARUS","BB":"BARBADOS","BD":"BANGLADESH","BH":"BAHRAIN","BS":"BAHAMAS","AZ":"AZERBAIJAN","AT":"AUSTRIA","AU":"AUSTRALIA","AW":"ARUBA","AM":"ARMENIA","AR":"ARGENTINA","AG":"ANTIGUA AND BARBUDA","AQ":"ANTARCTICA","AI":"ANGUILLA","AO":"ANGOLA","AD":"ANDORRA","AS":"AMERICAN SAMOA","DZ":"ALGERIA","AL":"ALBANIA","AX":"ÅLAND ISLANDS","AF":"AFGHANISTAN"}