<?xml version="1.0" encoding="UTF-8"?>
<FUNGRP AutoGen-Parameter-Version="1.0" DESC="LMTS General Facility"
    NAME="LMTSGeneralFacilityOR" ROWS="6" TYPE="T">
    <FUNCTION FUNCTYPE="GE" forGPC="Y">
        <MODULE DESC="Limit Management">LMTS</MODULE>
        <ID>F05030702666</ID>
        <NAME>AddFacilityType</NAME>
        <DESC>Add Facility Type</DESC>
    </FUNCTION>
    <FUNCTION FUNCTYPE="GE" forGPC="Y">
        <MODULE DESC="Limit Management">LMTS</MODULE>
        <ID>F05030702678</ID>
        <NAME>DeleteFacilityType</NAME>
        <DESC>Delete Facility Type</DESC>
    </FUNCTION>
    <FUNCTION FUNCTYPE="GE" forGPC="Y">
        <MODULE DESC="Limit Management">LMTS</MODULE>
        <ID>F05030702689</ID>
        <NAME>EditFacilityType</NAME>
        <DESC>Edit Facility Type</DESC>
    </FUNCTION>
    <FUNCTION FUNCTYPE="GE" forGPC="Y">
        <MODULE DESC="Limit Management">LMTS</MODULE>
        <ID>F05030702704</ID>
        <NAME>InquireFacilityType</NAME>
        <DESC>Inquire Facility Type</DESC>
    </FUNCTION>
    <FUNCTION FUNCTYPE="RE" forGPC="Y">
        <MODULE DESC="Limit Management">LMTS</MODULE>
        <ID>F05030702716</ID>
        <NAME>ReleaseFacilityType</NAME>
        <DESC>Release Facility Type</DESC>
    </FUNCTION>
    <FUNCTION FUNCTYPE="GE" forGPC="Y">
        <MODULE DESC="Limit Management">LMTS</MODULE>
        <ID>F05030702727</ID>
        <NAME>UnlockFacilityType</NAME>
        <DESC>Unlock Facility Type</DESC>
    </FUNCTION>
</FUNGRP>
