<?xml version="1.0" encoding="UTF-8"?>
<FUNGRP DESC="Invoice Maintenance" NAME="INVCEFFactoringOR" ROWS="2" TYPE="T" AutoGen-Parameter-Version="1.0">
    <FUNCTION FUNCTYPE="IQ" forGPC="Y">
        <MODULE DESC="Invoice Data">INVC</MODULE>
        <ID>cn4bRIgXGuwv</ID>
        <NAME>INVC_SCFEnquireEvent</NAME>
        <DESC>Enquire Invoice</DESC>
    </FUNCTION>
    <FUNCTION FUNCTYPE="IQ" forGPC="Y">
        <MODULE DESC="Invoice Data">INVC</MODULE>
        <ID>WPXTTxiii9On</ID>
        <NAME>INVC_SCFEnquireCRN</NAME>
        <DESC>Enquire CreditNote</DESC>
    </FUNCTION>
</FUNGRP>