<?xml version="1.0" encoding="UTF-8"?>
<FUNC>
    <FUNCTION>
        <MODULE TYPE="STD">STAN</MODULE>
        <MODULE_DESC>Standing Module</MODULE_DESC>
        <EVENT>Clause</EVENT>
        <CATALOGID/>
        <ID>F05030700265</ID>
        <NAME>Add Clause</NAME>
        <DESC>Add Clause</DESC>
        <FUNSHORTNAME>AddClause</FUNSHORTNAME>
        <LOCKCHECK>Y</LOCKCHECK>
        <HOLDMASTER>T</HOLDMASTER>
        <FUNCTYPE>GE</FUNCTYPE>
        <MAINCOMP name="STD Manager">STDManager</MAINCOMP>
        <ADDMASTER>N</ADDMASTER>
        <RIGHT_MSG/>
        <RIGHTJSP TMPLFILE=""/>
        <COMPTYPE/>
        <RELEASE>N</RELEASE>
        <SIGN>Y</SIGN>
    </FUNCTION>
    <SCREEN>
        <JSPFILE TMPLFILE="STD_Template.jsp">STAN_Clause.jsp</JSPFILE>
    </SCREEN>
    <FORM>
        <ID>F05030700266</ID>
        <NAME>Add Clause_FORM</NAME>
    </FORM>
    <VOUCHER>
        <ID>A05030700266</ID>
        <NAME>Add Clause_ACCOUT</NAME>
    </VOUCHER>
    <NOTIFY>
        <ID>N00000000084</ID>
        <NAME>Add Clause_NOTIFY</NAME>
    </NOTIFY>
</FUNC>
