<?xml version="1.0" encoding="UTF-8"?>
<TABLESTRUCTURE DATABASE="EEPDB" EETYPE="X" TABLE="BPOM_EM_DATA" ISView="N" Module="BPOM">
    <COLUMN>
        <NAME>DATA_STATUS</NAME>
        <DEFAULTVALUE/>
        <ALLOWNULL>YES</ALLOWNULL>
        <TYPE>VARCHAR2</TYPE>
        <ID>12</ID>
        <LENGTH>32</LENGTH>
        <PRECISION>0</PRECISION>
        <SCALE>0</SCALE>
    </COLUMN>
    <COLUMN>
        <NAME>C_USER_ID</NAME>
        <DEFAULTVALUE/>
        <ALLOWNULL>YES</ALLOWNULL>
        <TYPE>VARCHAR2</TYPE>
        <ID>12</ID>
        <LENGTH>32</LENGTH>
        <PRECISION>0</PRECISION>
        <SCALE>0</SCALE>
    </COLUMN>
    <COLUMN>
        <NAME>C_UNIT_CODE</NAME>
        <DEFAULTVALUE/>
        <ALLOWNULL>NO</ALLOWNULL>
        <TYPE>VARCHAR2</TYPE>
        <ID>12</ID>
        <LENGTH>12</LENGTH>
        <PRECISION>0</PRECISION>
        <SCALE>0</SCALE>
    </COLUMN>
    <COLUMN>
        <NAME>C_TRX_STATUS</NAME>
        <DEFAULTVALUE/>
        <ALLOWNULL>YES</ALLOWNULL>
        <TYPE>VARCHAR2</TYPE>
        <ID>12</ID>
        <LENGTH>1</LENGTH>
        <PRECISION>0</PRECISION>
        <SCALE>0</SCALE>
    </COLUMN>
    <COLUMN>
        <NAME>C_TRX_REF</NAME>
        <DEFAULTVALUE/>
        <ALLOWNULL>NO</ALLOWNULL>
        <TYPE>VARCHAR2</TYPE>
        <ID>12</ID>
        <LENGTH>40</LENGTH>
        <PRECISION>0</PRECISION>
        <SCALE>0</SCALE>
    </COLUMN>
    <COLUMN>
        <NAME>C_RELE_BY</NAME>
        <DEFAULTVALUE/>
        <ALLOWNULL>YES</ALLOWNULL>
        <TYPE>VARCHAR2</TYPE>
        <ID>12</ID>
        <LENGTH>32</LENGTH>
        <PRECISION>0</PRECISION>
        <SCALE>0</SCALE>
    </COLUMN>
    <COLUMN>
        <NAME>C_NOW_EVENT</NAME>
        <DEFAULTVALUE/>
        <ALLOWNULL>YES</ALLOWNULL>
        <TYPE>VARCHAR2</TYPE>
        <ID>12</ID>
        <LENGTH>20</LENGTH>
        <PRECISION>0</PRECISION>
        <SCALE>0</SCALE>
    </COLUMN>
    <COLUMN>
        <NAME>C_MODULE</NAME>
        <DEFAULTVALUE/>
        <ALLOWNULL>YES</ALLOWNULL>
        <TYPE>VARCHAR2</TYPE>
        <ID>12</ID>
        <LENGTH>4</LENGTH>
        <PRECISION>0</PRECISION>
        <SCALE>0</SCALE>
    </COLUMN>
    <COLUMN>
        <NAME>C_MAIN_REF</NAME>
        <DEFAULTVALUE/>
        <ALLOWNULL>NO</ALLOWNULL>
        <TYPE>VARCHAR2</TYPE>
        <ID>12</ID>
        <LENGTH>40</LENGTH>
        <PRECISION>0</PRECISION>
        <SCALE>0</SCALE>
    </COLUMN>
    <COLUMN>
        <NAME>C_LOCK_FUNC_ID</NAME>
        <DEFAULTVALUE/>
        <ALLOWNULL>YES</ALLOWNULL>
        <TYPE>VARCHAR2</TYPE>
        <ID>12</ID>
        <LENGTH>12</LENGTH>
        <PRECISION>0</PRECISION>
        <SCALE>0</SCALE>
    </COLUMN>
    <COLUMN>
        <NAME>C_LOCKED_OP</NAME>
        <DEFAULTVALUE/>
        <ALLOWNULL>YES</ALLOWNULL>
        <TYPE>VARCHAR2</TYPE>
        <ID>12</ID>
        <LENGTH>32</LENGTH>
        <PRECISION>0</PRECISION>
        <SCALE>0</SCALE>
    </COLUMN>
    <COLUMN>
        <NAME>C_LOCKED_FLAG</NAME>
        <DEFAULTVALUE/>
        <ALLOWNULL>YES</ALLOWNULL>
        <TYPE>VARCHAR2</TYPE>
        <ID>12</ID>
        <LENGTH>1</LENGTH>
        <PRECISION>0</PRECISION>
        <SCALE>0</SCALE>
    </COLUMN>
    <COLUMN>
        <NAME>C_HISTORY_EVENT_TIMES</NAME>
        <DEFAULTVALUE/>
        <ALLOWNULL>YES</ALLOWNULL>
        <TYPE>VARCHAR2</TYPE>
        <ID>12</ID>
        <LENGTH>256</LENGTH>
        <PRECISION>0</PRECISION>
        <SCALE>0</SCALE>
    </COLUMN>
    <COLUMN>
        <NAME>C_FUNC_SHORT_NAME</NAME>
        <DEFAULTVALUE/>
        <ALLOWNULL>YES</ALLOWNULL>
        <TYPE>VARCHAR2</TYPE>
        <ID>12</ID>
        <LENGTH>16</LENGTH>
        <PRECISION>0</PRECISION>
        <SCALE>0</SCALE>
    </COLUMN>
    <COLUMN>
        <NAME>C_EVENT_TIME</NAME>
        <DEFAULTVALUE/>
        <ALLOWNULL>YES</ALLOWNULL>
        <TYPE>VARCHAR2</TYPE>
        <ID>12</ID>
        <LENGTH>20</LENGTH>
        <PRECISION>0</PRECISION>
        <SCALE>0</SCALE>
    </COLUMN>
    <COLUMN>
        <NAME>C_EVENT_STATUS</NAME>
        <DEFAULTVALUE/>
        <ALLOWNULL>YES</ALLOWNULL>
        <TYPE>VARCHAR2</TYPE>
        <ID>12</ID>
        <LENGTH>1</LENGTH>
        <PRECISION>0</PRECISION>
        <SCALE>0</SCALE>
    </COLUMN>
    <COLUMN>
        <NAME>C_EVENT_NAME</NAME>
        <DEFAULTVALUE/>
        <ALLOWNULL>YES</ALLOWNULL>
        <TYPE>VARCHAR2</TYPE>
        <ID>12</ID>
        <LENGTH>20</LENGTH>
        <PRECISION>0</PRECISION>
        <SCALE>0</SCALE>
    </COLUMN>
    <COLUMN>
        <NAME>C_DO_NAME</NAME>
        <DEFAULTVALUE/>
        <ALLOWNULL>YES</ALLOWNULL>
        <TYPE>VARCHAR2</TYPE>
        <ID>12</ID>
        <LENGTH>255</LENGTH>
        <PRECISION>0</PRECISION>
        <SCALE>0</SCALE>
    </COLUMN>
    <COLUMN>
        <NAME>C_CUST_ID</NAME>
        <DEFAULTVALUE/>
        <ALLOWNULL>YES</ALLOWNULL>
        <TYPE>VARCHAR2</TYPE>
        <ID>12</ID>
        <LENGTH>32</LENGTH>
        <PRECISION>0</PRECISION>
        <SCALE>0</SCALE>
    </COLUMN>
    <COLUMN>
        <NAME>C_CP_UNIT_CODE1</NAME>
        <DEFAULTVALUE/>
        <ALLOWNULL>YES</ALLOWNULL>
        <TYPE>VARCHAR2</TYPE>
        <ID>12</ID>
        <LENGTH>12</LENGTH>
        <PRECISION>0</PRECISION>
        <SCALE>0</SCALE>
    </COLUMN>
    <COLUMN>
        <NAME>C_CP_UNIT_CODE</NAME>
        <DEFAULTVALUE/>
        <ALLOWNULL>YES</ALLOWNULL>
        <TYPE>VARCHAR2</TYPE>
        <ID>12</ID>
        <LENGTH>12</LENGTH>
        <PRECISION>0</PRECISION>
        <SCALE>0</SCALE>
    </COLUMN>
    <COLUMN>
        <NAME>C_BK_GROUP_ID</NAME>
        <DEFAULTVALUE/>
        <ALLOWNULL>YES</ALLOWNULL>
        <TYPE>VARCHAR2</TYPE>
        <ID>12</ID>
        <LENGTH>12</LENGTH>
        <PRECISION>0</PRECISION>
        <SCALE>0</SCALE>
    </COLUMN>
    <COLUMN>
        <NAME>BUYR_NM</NAME>
        <DEFAULTVALUE/>
        <ALLOWNULL>YES</ALLOWNULL>
        <TYPE>VARCHAR2</TYPE>
        <ID>12</ID>
        <LENGTH>70</LENGTH>
        <PRECISION>0</PRECISION>
        <SCALE>0</SCALE>
    </COLUMN>
    <COLUMN>
        <NAME>BUYR_MAIL_ADD</NAME>
        <DEFAULTVALUE/>
        <ALLOWNULL>YES</ALLOWNULL>
        <TYPE>VARCHAR2</TYPE>
        <ID>12</ID>
        <LENGTH>210</LENGTH>
        <PRECISION>0</PRECISION>
        <SCALE>0</SCALE>
    </COLUMN>
    <COLUMN>
        <NAME>BUYR_ID</NAME>
        <DEFAULTVALUE/>
        <ALLOWNULL>YES</ALLOWNULL>
        <TYPE>VARCHAR2</TYPE>
        <ID>12</ID>
        <LENGTH>40</LENGTH>
        <PRECISION>0</PRECISION>
        <SCALE>0</SCALE>
    </COLUMN>
    <COLUMN>
        <NAME>BUYR_FAX</NAME>
        <DEFAULTVALUE/>
        <ALLOWNULL>YES</ALLOWNULL>
        <TYPE>VARCHAR2</TYPE>
        <ID>12</ID>
        <LENGTH>30</LENGTH>
        <PRECISION>0</PRECISION>
        <SCALE>0</SCALE>
    </COLUMN>
    <COLUMN>
        <NAME>BUYR_EMAIL</NAME>
        <DEFAULTVALUE/>
        <ALLOWNULL>YES</ALLOWNULL>
        <TYPE>VARCHAR2</TYPE>
        <ID>12</ID>
        <LENGTH>50</LENGTH>
        <PRECISION>0</PRECISION>
        <SCALE>0</SCALE>
    </COLUMN>
    <COLUMN>
        <NAME>BUYR_CORR_MED</NAME>
        <DEFAULTVALUE/>
        <ALLOWNULL>YES</ALLOWNULL>
        <TYPE>VARCHAR2</TYPE>
        <ID>12</ID>
        <LENGTH>128</LENGTH>
        <PRECISION>0</PRECISION>
        <SCALE>0</SCALE>
    </COLUMN>
    <COLUMN>
        <NAME>BUYR_ADD3</NAME>
        <DEFAULTVALUE/>
        <ALLOWNULL>YES</ALLOWNULL>
        <TYPE>VARCHAR2</TYPE>
        <ID>12</ID>
        <LENGTH>35</LENGTH>
        <PRECISION>0</PRECISION>
        <SCALE>0</SCALE>
    </COLUMN>
    <COLUMN>
        <NAME>BUYR_ADD2</NAME>
        <DEFAULTVALUE/>
        <ALLOWNULL>YES</ALLOWNULL>
        <TYPE>VARCHAR2</TYPE>
        <ID>12</ID>
        <LENGTH>35</LENGTH>
        <PRECISION>0</PRECISION>
        <SCALE>0</SCALE>
    </COLUMN>
    <COLUMN>
        <NAME>BUYR_ADD1</NAME>
        <DEFAULTVALUE/>
        <ALLOWNULL>YES</ALLOWNULL>
        <TYPE>VARCHAR2</TYPE>
        <ID>12</ID>
        <LENGTH>35</LENGTH>
        <PRECISION>0</PRECISION>
        <SCALE>0</SCALE>
    </COLUMN>
    <COLUMN>
        <NAME>AI_DUE_DT</NAME>
        <DEFAULTVALUE/>
        <ALLOWNULL>YES</ALLOWNULL>
        <TYPE>DATE</TYPE>
        <ID>91</ID>
        <LENGTH>7</LENGTH>
        <PRECISION>0</PRECISION>
        <SCALE>0</SCALE>
    </COLUMN>
    <COLUMN>
        <NAME>ADV_BK_SW_TAG</NAME>
        <DEFAULTVALUE/>
        <ALLOWNULL>YES</ALLOWNULL>
        <TYPE>VARCHAR2</TYPE>
        <ID>12</ID>
        <LENGTH>1</LENGTH>
        <PRECISION>0</PRECISION>
        <SCALE>0</SCALE>
    </COLUMN>
    <COLUMN>
        <NAME>ADV_BK_SW_ADD</NAME>
        <DEFAULTVALUE/>
        <ALLOWNULL>YES</ALLOWNULL>
        <TYPE>VARCHAR2</TYPE>
        <ID>12</ID>
        <LENGTH>11</LENGTH>
        <PRECISION>0</PRECISION>
        <SCALE>0</SCALE>
    </COLUMN>
    <COLUMN>
        <NAME>ADV_BK_NM</NAME>
        <DEFAULTVALUE/>
        <ALLOWNULL>YES</ALLOWNULL>
        <TYPE>VARCHAR2</TYPE>
        <ID>12</ID>
        <LENGTH>35</LENGTH>
        <PRECISION>0</PRECISION>
        <SCALE>0</SCALE>
    </COLUMN>
    <COLUMN>
        <NAME>ADV_BK_MAIL_ADD</NAME>
        <DEFAULTVALUE/>
        <ALLOWNULL>YES</ALLOWNULL>
        <TYPE>VARCHAR2</TYPE>
        <ID>12</ID>
        <LENGTH>210</LENGTH>
        <PRECISION>0</PRECISION>
        <SCALE>0</SCALE>
    </COLUMN>
    <COLUMN>
        <NAME>ADV_BK_ID</NAME>
        <DEFAULTVALUE/>
        <ALLOWNULL>YES</ALLOWNULL>
        <TYPE>VARCHAR2</TYPE>
        <ID>12</ID>
        <LENGTH>16</LENGTH>
        <PRECISION>0</PRECISION>
        <SCALE>0</SCALE>
    </COLUMN>
    <COLUMN>
        <NAME>ADV_BK_ADD3</NAME>
        <DEFAULTVALUE/>
        <ALLOWNULL>YES</ALLOWNULL>
        <TYPE>VARCHAR2</TYPE>
        <ID>12</ID>
        <LENGTH>35</LENGTH>
        <PRECISION>0</PRECISION>
        <SCALE>0</SCALE>
    </COLUMN>
    <COLUMN>
        <NAME>ADV_BK_ADD2</NAME>
        <DEFAULTVALUE/>
        <ALLOWNULL>YES</ALLOWNULL>
        <TYPE>VARCHAR2</TYPE>
        <ID>12</ID>
        <LENGTH>35</LENGTH>
        <PRECISION>0</PRECISION>
        <SCALE>0</SCALE>
    </COLUMN>
    <COLUMN>
        <NAME>ADV_BK_ADD1</NAME>
        <DEFAULTVALUE/>
        <ALLOWNULL>YES</ALLOWNULL>
        <TYPE>VARCHAR2</TYPE>
        <ID>12</ID>
        <LENGTH>35</LENGTH>
        <PRECISION>0</PRECISION>
        <SCALE>0</SCALE>
    </COLUMN>
    <COLUMN>
        <NAME>T_SYS_REL_TIME</NAME>
        <DEFAULTVALUE/>
        <ALLOWNULL>YES</ALLOWNULL>
        <TYPE>DATE</TYPE>
        <ID>91</ID>
        <LENGTH>7</LENGTH>
        <PRECISION>0</PRECISION>
        <SCALE>0</SCALE>
    </COLUMN>
    <COLUMN>
        <NAME>T_SYS_OP_TIME</NAME>
        <DEFAULTVALUE/>
        <ALLOWNULL>YES</ALLOWNULL>
        <TYPE>DATE</TYPE>
        <ID>91</ID>
        <LENGTH>7</LENGTH>
        <PRECISION>0</PRECISION>
        <SCALE>0</SCALE>
    </COLUMN>
    <COLUMN>
        <NAME>T_SVR_GMT</NAME>
        <DEFAULTVALUE/>
        <ALLOWNULL>YES</ALLOWNULL>
        <TYPE>DATE</TYPE>
        <ID>91</ID>
        <LENGTH>7</LENGTH>
        <PRECISION>0</PRECISION>
        <SCALE>0</SCALE>
    </COLUMN>
    <COLUMN>
        <NAME>T_RELE_TIME</NAME>
        <DEFAULTVALUE/>
        <ALLOWNULL>YES</ALLOWNULL>
        <TYPE>DATE</TYPE>
        <ID>91</ID>
        <LENGTH>7</LENGTH>
        <PRECISION>0</PRECISION>
        <SCALE>0</SCALE>
    </COLUMN>
    <COLUMN>
        <NAME>TSU_WEIG_REQ</NAME>
        <DEFAULTVALUE/>
        <ALLOWNULL>YES</ALLOWNULL>
        <TYPE>VARCHAR2</TYPE>
        <ID>12</ID>
        <LENGTH>1</LENGTH>
        <PRECISION>0</PRECISION>
        <SCALE>0</SCALE>
    </COLUMN>
    <COLUMN>
        <NAME>TSU_TRX_DTTM</NAME>
        <DEFAULTVALUE/>
        <ALLOWNULL>YES</ALLOWNULL>
        <TYPE>VARCHAR2</TYPE>
        <ID>12</ID>
        <LENGTH>50</LENGTH>
        <PRECISION>0</PRECISION>
        <SCALE>0</SCALE>
    </COLUMN>
    <COLUMN>
        <NAME>TSU_TRAN_REQ</NAME>
        <DEFAULTVALUE/>
        <ALLOWNULL>YES</ALLOWNULL>
        <TYPE>VARCHAR2</TYPE>
        <ID>12</ID>
        <LENGTH>1</LENGTH>
        <PRECISION>0</PRECISION>
        <SCALE>0</SCALE>
    </COLUMN>
    <COLUMN>
        <NAME>TSU_SEL_SUB_BK</NAME>
        <DEFAULTVALUE/>
        <ALLOWNULL>YES</ALLOWNULL>
        <TYPE>VARCHAR2</TYPE>
        <ID>12</ID>
        <LENGTH>11</LENGTH>
        <PRECISION>0</PRECISION>
        <SCALE>0</SCALE>
    </COLUMN>
    <COLUMN>
        <NAME>TSU_QUAT_REQ</NAME>
        <DEFAULTVALUE/>
        <ALLOWNULL>YES</ALLOWNULL>
        <TYPE>VARCHAR2</TYPE>
        <ID>12</ID>
        <LENGTH>1</LENGTH>
        <PRECISION>0</PRECISION>
        <SCALE>0</SCALE>
    </COLUMN>
    <COLUMN>
        <NAME>TSU_QUAN_REQ</NAME>
        <DEFAULTVALUE/>
        <ALLOWNULL>YES</ALLOWNULL>
        <TYPE>VARCHAR2</TYPE>
        <ID>12</ID>
        <LENGTH>1</LENGTH>
        <PRECISION>0</PRECISION>
        <SCALE>0</SCALE>
    </COLUMN>
    <COLUMN>
        <NAME>TSU_PMT_AMT</NAME>
        <DEFAULTVALUE>0.0</DEFAULTVALUE>
        <ALLOWNULL>YES</ALLOWNULL>
        <TYPE>NUMBER</TYPE>
        <ID>2</ID>
        <LENGTH>22</LENGTH>
        <PRECISION>18</PRECISION>
        <SCALE>3</SCALE>
    </COLUMN>
    <COLUMN>
        <NAME>TSU_PHYT_REQ</NAME>
        <DEFAULTVALUE/>
        <ALLOWNULL>YES</ALLOWNULL>
        <TYPE>VARCHAR2</TYPE>
        <ID>12</ID>
        <LENGTH>1</LENGTH>
        <PRECISION>0</PRECISION>
        <SCALE>0</SCALE>
    </COLUMN>
    <COLUMN>
        <NAME>TSU_PAY_AMT</NAME>
        <DEFAULTVALUE>0.0</DEFAULTVALUE>
        <ALLOWNULL>YES</ALLOWNULL>
        <TYPE>NUMBER</TYPE>
        <ID>2</ID>
        <LENGTH>22</LENGTH>
        <PRECISION>18</PRECISION>
        <SCALE>3</SCALE>
    </COLUMN>
    <COLUMN>
        <NAME>TSU_ORIG_REQ</NAME>
        <DEFAULTVALUE/>
        <ALLOWNULL>YES</ALLOWNULL>
        <TYPE>VARCHAR2</TYPE>
        <ID>12</ID>
        <LENGTH>1</LENGTH>
        <PRECISION>0</PRECISION>
        <SCALE>0</SCALE>
    </COLUMN>
    <COLUMN>
        <NAME>TSU_INSU_REQ</NAME>
        <DEFAULTVALUE/>
        <ALLOWNULL>YES</ALLOWNULL>
        <TYPE>VARCHAR2</TYPE>
        <ID>12</ID>
        <LENGTH>1</LENGTH>
        <PRECISION>0</PRECISION>
        <SCALE>0</SCALE>
    </COLUMN>
    <COLUMN>
        <NAME>TSU_INCOTMS_LCTN</NAME>
        <DEFAULTVALUE/>
        <ALLOWNULL>YES</ALLOWNULL>
        <TYPE>VARCHAR2</TYPE>
        <ID>12</ID>
        <LENGTH>35</LENGTH>
        <PRECISION>0</PRECISION>
        <SCALE>0</SCALE>
    </COLUMN>
    <COLUMN>
        <NAME>TSU_IDX</NAME>
        <DEFAULTVALUE/>
        <ALLOWNULL>YES</ALLOWNULL>
        <TYPE>VARCHAR2</TYPE>
        <ID>12</ID>
        <LENGTH>35</LENGTH>
        <PRECISION>0</PRECISION>
        <SCALE>0</SCALE>
    </COLUMN>
    <COLUMN>
        <NAME>TSU_IAFT_TP</NAME>
        <DEFAULTVALUE/>
        <ALLOWNULL>YES</ALLOWNULL>
        <TYPE>VARCHAR2</TYPE>
        <ID>12</ID>
        <LENGTH>35</LENGTH>
        <PRECISION>0</PRECISION>
        <SCALE>0</SCALE>
    </COLUMN>
    <COLUMN>
        <NAME>TSU_IAFT_OT_TP</NAME>
        <DEFAULTVALUE/>
        <ALLOWNULL>YES</ALLOWNULL>
        <TYPE>VARCHAR2</TYPE>
        <ID>12</ID>
        <LENGTH>35</LENGTH>
        <PRECISION>0</PRECISION>
        <SCALE>0</SCALE>
    </COLUMN>
    <COLUMN>
        <NAME>TSU_HEAL_REQ</NAME>
        <DEFAULTVALUE/>
        <ALLOWNULL>YES</ALLOWNULL>
        <TYPE>VARCHAR2</TYPE>
        <ID>12</ID>
        <LENGTH>1</LENGTH>
        <PRECISION>0</PRECISION>
        <SCALE>0</SCALE>
    </COLUMN>
    <COLUMN>
        <NAME>TSU_FININST_NM</NAME>
        <DEFAULTVALUE/>
        <ALLOWNULL>YES</ALLOWNULL>
        <TYPE>VARCHAR2</TYPE>
        <ID>12</ID>
        <LENGTH>35</LENGTH>
        <PRECISION>0</PRECISION>
        <SCALE>0</SCALE>
    </COLUMN>
    <COLUMN>
        <NAME>TSU_FININST_BIC</NAME>
        <DEFAULTVALUE/>
        <ALLOWNULL>YES</ALLOWNULL>
        <TYPE>VARCHAR2</TYPE>
        <ID>12</ID>
        <LENGTH>11</LENGTH>
        <PRECISION>0</PRECISION>
        <SCALE>0</SCALE>
    </COLUMN>
    <COLUMN>
        <NAME>TSU_COMM_REQ</NAME>
        <DEFAULTVALUE/>
        <ALLOWNULL>YES</ALLOWNULL>
        <TYPE>VARCHAR2</TYPE>
        <ID>12</ID>
        <LENGTH>1</LENGTH>
        <PRECISION>0</PRECISION>
        <SCALE>0</SCALE>
    </COLUMN>
    <COLUMN>
        <NAME>TSU_COMM_REF</NAME>
        <DEFAULTVALUE/>
        <ALLOWNULL>YES</ALLOWNULL>
        <TYPE>VARCHAR2</TYPE>
        <ID>12</ID>
        <LENGTH>35</LENGTH>
        <PRECISION>0</PRECISION>
        <SCALE>0</SCALE>
    </COLUMN>
    <COLUMN>
        <NAME>TSU_COMM_DT</NAME>
        <DEFAULTVALUE/>
        <ALLOWNULL>YES</ALLOWNULL>
        <TYPE>DATE</TYPE>
        <ID>91</ID>
        <LENGTH>7</LENGTH>
        <PRECISION>0</PRECISION>
        <SCALE>0</SCALE>
    </COLUMN>
    <COLUMN>
        <NAME>TSU_COMM_AMT</NAME>
        <DEFAULTVALUE>0.0</DEFAULTVALUE>
        <ALLOWNULL>YES</ALLOWNULL>
        <TYPE>NUMBER</TYPE>
        <ID>2</ID>
        <LENGTH>22</LENGTH>
        <PRECISION>18</PRECISION>
        <SCALE>3</SCALE>
    </COLUMN>
    <COLUMN>
        <NAME>TSU_CMON_SUB_REF</NAME>
        <DEFAULTVALUE/>
        <ALLOWNULL>YES</ALLOWNULL>
        <TYPE>VARCHAR2</TYPE>
        <ID>12</ID>
        <LENGTH>35</LENGTH>
        <PRECISION>0</PRECISION>
        <SCALE>0</SCALE>
    </COLUMN>
    <COLUMN>
        <NAME>TSU_CDTRAC_TPID</NAME>
        <DEFAULTVALUE/>
        <ALLOWNULL>YES</ALLOWNULL>
        <TYPE>VARCHAR2</TYPE>
        <ID>12</ID>
        <LENGTH>35</LENGTH>
        <PRECISION>0</PRECISION>
        <SCALE>0</SCALE>
    </COLUMN>
    <COLUMN>
        <NAME>TSU_CDTRAC_TPCD</NAME>
        <DEFAULTVALUE/>
        <ALLOWNULL>YES</ALLOWNULL>
        <TYPE>VARCHAR2</TYPE>
        <ID>12</ID>
        <LENGTH>20</LENGTH>
        <PRECISION>0</PRECISION>
        <SCALE>0</SCALE>
    </COLUMN>
    <COLUMN>
        <NAME>TSU_CDTRAC_NM</NAME>
        <DEFAULTVALUE/>
        <ALLOWNULL>YES</ALLOWNULL>
        <TYPE>VARCHAR2</TYPE>
        <ID>12</ID>
        <LENGTH>70</LENGTH>
        <PRECISION>0</PRECISION>
        <SCALE>0</SCALE>
    </COLUMN>
    <COLUMN>
        <NAME>TSU_CDTRAC_CCY</NAME>
        <DEFAULTVALUE/>
        <ALLOWNULL>YES</ALLOWNULL>
        <TYPE>VARCHAR2</TYPE>
        <ID>12</ID>
        <LENGTH>3</LENGTH>
        <PRECISION>0</PRECISION>
        <SCALE>0</SCALE>
    </COLUMN>
    <COLUMN>
        <NAME>TSU_CCY</NAME>
        <DEFAULTVALUE/>
        <ALLOWNULL>YES</ALLOWNULL>
        <TYPE>VARCHAR2</TYPE>
        <ID>12</ID>
        <LENGTH>3</LENGTH>
        <PRECISION>0</PRECISION>
        <SCALE>0</SCALE>
    </COLUMN>
    <COLUMN>
        <NAME>TSU_BUYER_SUB_BK</NAME>
        <DEFAULTVALUE/>
        <ALLOWNULL>YES</ALLOWNULL>
        <TYPE>VARCHAR2</TYPE>
        <ID>12</ID>
        <LENGTH>11</LENGTH>
        <PRECISION>0</PRECISION>
        <SCALE>0</SCALE>
    </COLUMN>
    <COLUMN>
        <NAME>TSU_BENE_UPIC</NAME>
        <DEFAULTVALUE/>
        <ALLOWNULL>YES</ALLOWNULL>
        <TYPE>VARCHAR2</TYPE>
        <ID>12</ID>
        <LENGTH>35</LENGTH>
        <PRECISION>0</PRECISION>
        <SCALE>0</SCALE>
    </COLUMN>
    <COLUMN>
        <NAME>TSU_BENE_IBAN</NAME>
        <DEFAULTVALUE/>
        <ALLOWNULL>YES</ALLOWNULL>
        <TYPE>VARCHAR2</TYPE>
        <ID>12</ID>
        <LENGTH>35</LENGTH>
        <PRECISION>0</PRECISION>
        <SCALE>0</SCALE>
    </COLUMN>
    <COLUMN>
        <NAME>TSU_BENE_BBAN</NAME>
        <DEFAULTVALUE/>
        <ALLOWNULL>YES</ALLOWNULL>
        <TYPE>VARCHAR2</TYPE>
        <ID>12</ID>
        <LENGTH>35</LENGTH>
        <PRECISION>0</PRECISION>
        <SCALE>0</SCALE>
    </COLUMN>
    <COLUMN>
        <NAME>TSU_BENE_ACC</NAME>
        <DEFAULTVALUE/>
        <ALLOWNULL>YES</ALLOWNULL>
        <TYPE>VARCHAR2</TYPE>
        <ID>12</ID>
        <LENGTH>35</LENGTH>
        <PRECISION>0</PRECISION>
        <SCALE>0</SCALE>
    </COLUMN>
    <COLUMN>
        <NAME>TSU_ANAY_REQ</NAME>
        <DEFAULTVALUE/>
        <ALLOWNULL>YES</ALLOWNULL>
        <TYPE>VARCHAR2</TYPE>
        <ID>12</ID>
        <LENGTH>1</LENGTH>
        <PRECISION>0</PRECISION>
        <SCALE>0</SCALE>
    </COLUMN>
    <COLUMN>
        <NAME>TRX_DT</NAME>
        <DEFAULTVALUE/>
        <ALLOWNULL>YES</ALLOWNULL>
        <TYPE>DATE</TYPE>
        <ID>91</ID>
        <LENGTH>7</LENGTH>
        <PRECISION>0</PRECISION>
        <SCALE>0</SCALE>
    </COLUMN>
    <COLUMN>
        <NAME>SUPLR_NM</NAME>
        <DEFAULTVALUE/>
        <ALLOWNULL>YES</ALLOWNULL>
        <TYPE>VARCHAR2</TYPE>
        <ID>12</ID>
        <LENGTH>60</LENGTH>
        <PRECISION>0</PRECISION>
        <SCALE>0</SCALE>
    </COLUMN>
    <COLUMN>
        <NAME>SUPLR_MAIL_ADD</NAME>
        <DEFAULTVALUE/>
        <ALLOWNULL>YES</ALLOWNULL>
        <TYPE>VARCHAR2</TYPE>
        <ID>12</ID>
        <LENGTH>210</LENGTH>
        <PRECISION>0</PRECISION>
        <SCALE>0</SCALE>
    </COLUMN>
    <COLUMN>
        <NAME>SUPLR_ID</NAME>
        <DEFAULTVALUE/>
        <ALLOWNULL>YES</ALLOWNULL>
        <TYPE>VARCHAR2</TYPE>
        <ID>12</ID>
        <LENGTH>40</LENGTH>
        <PRECISION>0</PRECISION>
        <SCALE>0</SCALE>
    </COLUMN>
    <COLUMN>
        <NAME>SUPLR_FAX</NAME>
        <DEFAULTVALUE/>
        <ALLOWNULL>YES</ALLOWNULL>
        <TYPE>VARCHAR2</TYPE>
        <ID>12</ID>
        <LENGTH>30</LENGTH>
        <PRECISION>0</PRECISION>
        <SCALE>0</SCALE>
    </COLUMN>
    <COLUMN>
        <NAME>SUPLR_EMAIL</NAME>
        <DEFAULTVALUE/>
        <ALLOWNULL>YES</ALLOWNULL>
        <TYPE>VARCHAR2</TYPE>
        <ID>12</ID>
        <LENGTH>256</LENGTH>
        <PRECISION>0</PRECISION>
        <SCALE>0</SCALE>
    </COLUMN>
    <COLUMN>
        <NAME>SUPLR_CORR_MED</NAME>
        <DEFAULTVALUE/>
        <ALLOWNULL>YES</ALLOWNULL>
        <TYPE>VARCHAR2</TYPE>
        <ID>12</ID>
        <LENGTH>128</LENGTH>
        <PRECISION>0</PRECISION>
        <SCALE>0</SCALE>
    </COLUMN>
    <COLUMN>
        <NAME>SUPLR_ADD3</NAME>
        <DEFAULTVALUE/>
        <ALLOWNULL>YES</ALLOWNULL>
        <TYPE>VARCHAR2</TYPE>
        <ID>12</ID>
        <LENGTH>70</LENGTH>
        <PRECISION>0</PRECISION>
        <SCALE>0</SCALE>
    </COLUMN>
    <COLUMN>
        <NAME>SUPLR_ADD2</NAME>
        <DEFAULTVALUE/>
        <ALLOWNULL>YES</ALLOWNULL>
        <TYPE>VARCHAR2</TYPE>
        <ID>12</ID>
        <LENGTH>60</LENGTH>
        <PRECISION>0</PRECISION>
        <SCALE>0</SCALE>
    </COLUMN>
    <COLUMN>
        <NAME>SUPLR_ADD1</NAME>
        <DEFAULTVALUE/>
        <ALLOWNULL>YES</ALLOWNULL>
        <TYPE>VARCHAR2</TYPE>
        <ID>12</ID>
        <LENGTH>60</LENGTH>
        <PRECISION>0</PRECISION>
        <SCALE>0</SCALE>
    </COLUMN>
    <COLUMN>
        <NAME>RADIOGROUP1</NAME>
        <DEFAULTVALUE/>
        <ALLOWNULL>YES</ALLOWNULL>
        <TYPE>VARCHAR2</TYPE>
        <ID>12</ID>
        <LENGTH>5</LENGTH>
        <PRECISION>0</PRECISION>
        <SCALE>0</SCALE>
    </COLUMN>
    <COLUMN>
        <NAME>RADIOGROUP0</NAME>
        <DEFAULTVALUE/>
        <ALLOWNULL>YES</ALLOWNULL>
        <TYPE>VARCHAR2</TYPE>
        <ID>12</ID>
        <LENGTH>5</LENGTH>
        <PRECISION>0</PRECISION>
        <SCALE>0</SCALE>
    </COLUMN>
    <COLUMN>
        <NAME>LIAB_ACNO</NAME>
        <DEFAULTVALUE/>
        <ALLOWNULL>YES</ALLOWNULL>
        <TYPE>VARCHAR2</TYPE>
        <ID>12</ID>
        <LENGTH>35</LENGTH>
        <PRECISION>0</PRECISION>
        <SCALE>0</SCALE>
    </COLUMN>
    <COLUMN>
        <NAME>I_PRE_EVENT_TIMES</NAME>
        <DEFAULTVALUE/>
        <ALLOWNULL>YES</ALLOWNULL>
        <TYPE>NUMBER</TYPE>
        <ID>2</ID>
        <LENGTH>22</LENGTH>
        <PRECISION>0</PRECISION>
        <SCALE>0</SCALE>
    </COLUMN>
    <COLUMN>
        <NAME>I_EVENT_TIMES</NAME>
        <DEFAULTVALUE/>
        <ALLOWNULL>YES</ALLOWNULL>
        <TYPE>NUMBER</TYPE>
        <ID>2</ID>
        <LENGTH>22</LENGTH>
        <PRECISION>0</PRECISION>
        <SCALE>0</SCALE>
    </COLUMN>
    <COLUMN>
        <NAME>I_CROSS_ETIMES</NAME>
        <DEFAULTVALUE/>
        <ALLOWNULL>YES</ALLOWNULL>
        <TYPE>NUMBER</TYPE>
        <ID>2</ID>
        <LENGTH>22</LENGTH>
        <PRECISION>0</PRECISION>
        <SCALE>0</SCALE>
    </COLUMN>
    <COLUMN>
        <NAME>ISSUE_BK_SW_TAG</NAME>
        <DEFAULTVALUE/>
        <ALLOWNULL>YES</ALLOWNULL>
        <TYPE>VARCHAR2</TYPE>
        <ID>12</ID>
        <LENGTH>1</LENGTH>
        <PRECISION>0</PRECISION>
        <SCALE>0</SCALE>
    </COLUMN>
    <COLUMN>
        <NAME>ISSUE_BK_SW_ADD</NAME>
        <DEFAULTVALUE/>
        <ALLOWNULL>YES</ALLOWNULL>
        <TYPE>VARCHAR2</TYPE>
        <ID>12</ID>
        <LENGTH>11</LENGTH>
        <PRECISION>0</PRECISION>
        <SCALE>0</SCALE>
    </COLUMN>
    <COLUMN>
        <NAME>ISSUE_BK_NM</NAME>
        <DEFAULTVALUE/>
        <ALLOWNULL>YES</ALLOWNULL>
        <TYPE>VARCHAR2</TYPE>
        <ID>12</ID>
        <LENGTH>35</LENGTH>
        <PRECISION>0</PRECISION>
        <SCALE>0</SCALE>
    </COLUMN>
    <COLUMN>
        <NAME>ISSUE_BK_MAIL_ADD</NAME>
        <DEFAULTVALUE/>
        <ALLOWNULL>YES</ALLOWNULL>
        <TYPE>VARCHAR2</TYPE>
        <ID>12</ID>
        <LENGTH>210</LENGTH>
        <PRECISION>0</PRECISION>
        <SCALE>0</SCALE>
    </COLUMN>
    <COLUMN>
        <NAME>ISSUE_BK_ID</NAME>
        <DEFAULTVALUE/>
        <ALLOWNULL>YES</ALLOWNULL>
        <TYPE>VARCHAR2</TYPE>
        <ID>12</ID>
        <LENGTH>16</LENGTH>
        <PRECISION>0</PRECISION>
        <SCALE>0</SCALE>
    </COLUMN>
    <COLUMN>
        <NAME>ISSUE_BK_ADD3</NAME>
        <DEFAULTVALUE/>
        <ALLOWNULL>YES</ALLOWNULL>
        <TYPE>VARCHAR2</TYPE>
        <ID>12</ID>
        <LENGTH>35</LENGTH>
        <PRECISION>0</PRECISION>
        <SCALE>0</SCALE>
    </COLUMN>
    <COLUMN>
        <NAME>ISSUE_BK_ADD2</NAME>
        <DEFAULTVALUE/>
        <ALLOWNULL>YES</ALLOWNULL>
        <TYPE>VARCHAR2</TYPE>
        <ID>12</ID>
        <LENGTH>35</LENGTH>
        <PRECISION>0</PRECISION>
        <SCALE>0</SCALE>
    </COLUMN>
    <COLUMN>
        <NAME>ISSUE_BK_ADD1</NAME>
        <DEFAULTVALUE/>
        <ALLOWNULL>YES</ALLOWNULL>
        <TYPE>VARCHAR2</TYPE>
        <ID>12</ID>
        <LENGTH>35</LENGTH>
        <PRECISION>0</PRECISION>
        <SCALE>0</SCALE>
    </COLUMN>
    <COLUMN>
        <NAME>D_SYS_REL_DATE</NAME>
        <DEFAULTVALUE/>
        <ALLOWNULL>YES</ALLOWNULL>
        <TYPE>DATE</TYPE>
        <ID>91</ID>
        <LENGTH>7</LENGTH>
        <PRECISION>0</PRECISION>
        <SCALE>0</SCALE>
    </COLUMN>
    <COLUMN>
        <NAME>D_SYS_OP_DATE</NAME>
        <DEFAULTVALUE/>
        <ALLOWNULL>YES</ALLOWNULL>
        <TYPE>DATE</TYPE>
        <ID>91</ID>
        <LENGTH>7</LENGTH>
        <PRECISION>0</PRECISION>
        <SCALE>0</SCALE>
    </COLUMN>
    <COLUMN>
        <NAME>D_SVR_GMT</NAME>
        <DEFAULTVALUE/>
        <ALLOWNULL>YES</ALLOWNULL>
        <TYPE>DATE</TYPE>
        <ID>91</ID>
        <LENGTH>7</LENGTH>
        <PRECISION>0</PRECISION>
        <SCALE>0</SCALE>
    </COLUMN>
    <COLUMN>
        <NAME>D_RELE_DATE</NAME>
        <DEFAULTVALUE/>
        <ALLOWNULL>YES</ALLOWNULL>
        <TYPE>DATE</TYPE>
        <ID>91</ID>
        <LENGTH>7</LENGTH>
        <PRECISION>0</PRECISION>
        <SCALE>0</SCALE>
    </COLUMN>
    <COLUMN>
        <NAME>D_CREA_DATE</NAME>
        <DEFAULTVALUE/>
        <ALLOWNULL>YES</ALLOWNULL>
        <TYPE>DATE</TYPE>
        <ID>91</ID>
        <LENGTH>7</LENGTH>
        <PRECISION>0</PRECISION>
        <SCALE>0</SCALE>
    </COLUMN>
    <PKEY>
        <PKNAME ID="12">C_MAIN_REF</PKNAME>
        <PKNAME ID="12">C_TRX_REF</PKNAME>
        <PKNAME ID="12">C_UNIT_CODE</PKNAME>
    </PKEY>
    <FKEY/>
</TABLESTRUCTURE>