<?xml version="1.0" encoding="UTF-8"?>
<TABLESTRUCTURE DATABASE="EEPDB" EETYPE="" TABLE="CLAIM_DO" ISView="N" Module="">
    <COLUMN>
        <NAME>ORDER_NO</NAME>
        <DEFAULTVALUE/>
        <ALLOWNULL>YES</ALLOWNULL>
        <TYPE>NUMBER</TYPE>
        <ID>2</ID>
        <LENGTH>22</LENGTH>
        <PRECISION>0</PRECISION>
        <SCALE>0</SCALE>
    </COLUMN>
    <COLUMN>
        <NAME>I_SEQ_NUM</NAME>
        <DEFAULTVALUE/>
        <ALLOWNULL>YES</ALLOWNULL>
        <TYPE>NUMBER</TYPE>
        <ID>2</ID>
        <LENGTH>22</LENGTH>
        <PRECISION>0</PRECISION>
        <SCALE>0</SCALE>
    </COLUMN>
    <COLUMN>
        <NAME>DEBITHEADERFORCLAIMDO</NAME>
        <DEFAULTVALUE/>
        <ALLOWNULL>YES</ALLOWNULL>
        <TYPE>CLOB</TYPE>
        <ID>2005</ID>
        <LENGTH>4000</LENGTH>
        <PRECISION>0</PRECISION>
        <SCALE>0</SCALE>
    </COLUMN>
    <COLUMN>
        <NAME>C_UNIT_CODE</NAME>
        <DEFAULTVALUE/>
        <ALLOWNULL>YES</ALLOWNULL>
        <TYPE>VARCHAR2</TYPE>
        <ID>12</ID>
        <LENGTH>12</LENGTH>
        <PRECISION>0</PRECISION>
        <SCALE>0</SCALE>
    </COLUMN>
    <COLUMN>
        <NAME>C_MAIN_REF</NAME>
        <DEFAULTVALUE/>
        <ALLOWNULL>YES</ALLOWNULL>
        <TYPE>VARCHAR2</TYPE>
        <ID>12</ID>
        <LENGTH>40</LENGTH>
        <PRECISION>0</PRECISION>
        <SCALE>0</SCALE>
    </COLUMN>
    <COLUMN>
        <NAME>C_DO_NAME</NAME>
        <DEFAULTVALUE/>
        <ALLOWNULL>YES</ALLOWNULL>
        <TYPE>VARCHAR2</TYPE>
        <ID>12</ID>
        <LENGTH>255</LENGTH>
        <PRECISION>0</PRECISION>
        <SCALE>0</SCALE>
    </COLUMN>
    <COLUMN>
        <NAME>CREDITHEADERFORCLAIMDO</NAME>
        <DEFAULTVALUE/>
        <ALLOWNULL>YES</ALLOWNULL>
        <TYPE>CLOB</TYPE>
        <ID>2005</ID>
        <LENGTH>4000</LENGTH>
        <PRECISION>0</PRECISION>
        <SCALE>0</SCALE>
    </COLUMN>
    <COLUMN>
        <NAME>CLM_TRX_CCY_AMT</NAME>
        <DEFAULTVALUE/>
        <ALLOWNULL>YES</ALLOWNULL>
        <TYPE>NUMBER</TYPE>
        <ID>2</ID>
        <LENGTH>22</LENGTH>
        <PRECISION>18</PRECISION>
        <SCALE>3</SCALE>
    </COLUMN>
    <COLUMN>
        <NAME>CLM_STLMNT_THU</NAME>
        <DEFAULTVALUE/>
        <ALLOWNULL>YES</ALLOWNULL>
        <TYPE>VARCHAR2</TYPE>
        <ID>12</ID>
        <LENGTH>128</LENGTH>
        <PRECISION>0</PRECISION>
        <SCALE>0</SCALE>
    </COLUMN>
    <COLUMN>
        <NAME>CLM_REF</NAME>
        <DEFAULTVALUE/>
        <ALLOWNULL>NO</ALLOWNULL>
        <TYPE>VARCHAR2</TYPE>
        <ID>12</ID>
        <LENGTH>16</LENGTH>
        <PRECISION>0</PRECISION>
        <SCALE>0</SCALE>
    </COLUMN>
    <COLUMN>
        <NAME>CLM_CCY</NAME>
        <DEFAULTVALUE/>
        <ALLOWNULL>YES</ALLOWNULL>
        <TYPE>VARCHAR2</TYPE>
        <ID>12</ID>
        <LENGTH>3</LENGTH>
        <PRECISION>0</PRECISION>
        <SCALE>0</SCALE>
    </COLUMN>
    <COLUMN>
        <NAME>CLM_BK_SW_TAG</NAME>
        <DEFAULTVALUE/>
        <ALLOWNULL>YES</ALLOWNULL>
        <TYPE>VARCHAR2</TYPE>
        <ID>12</ID>
        <LENGTH>1</LENGTH>
        <PRECISION>0</PRECISION>
        <SCALE>0</SCALE>
    </COLUMN>
    <COLUMN>
        <NAME>CLM_BK_SW_ADD</NAME>
        <DEFAULTVALUE/>
        <ALLOWNULL>YES</ALLOWNULL>
        <TYPE>VARCHAR2</TYPE>
        <ID>12</ID>
        <LENGTH>11</LENGTH>
        <PRECISION>0</PRECISION>
        <SCALE>0</SCALE>
    </COLUMN>
    <COLUMN>
        <NAME>CLM_BK_NOTES</NAME>
        <DEFAULTVALUE/>
        <ALLOWNULL>YES</ALLOWNULL>
        <TYPE>CLOB</TYPE>
        <ID>2005</ID>
        <LENGTH>4000</LENGTH>
        <PRECISION>0</PRECISION>
        <SCALE>0</SCALE>
    </COLUMN>
    <COLUMN>
        <NAME>CLM_BK_NM</NAME>
        <DEFAULTVALUE/>
        <ALLOWNULL>YES</ALLOWNULL>
        <TYPE>VARCHAR2</TYPE>
        <ID>12</ID>
        <LENGTH>35</LENGTH>
        <PRECISION>0</PRECISION>
        <SCALE>0</SCALE>
    </COLUMN>
    <COLUMN>
        <NAME>CLM_BK_MAIL_ADD</NAME>
        <DEFAULTVALUE/>
        <ALLOWNULL>YES</ALLOWNULL>
        <TYPE>VARCHAR2</TYPE>
        <ID>12</ID>
        <LENGTH>210</LENGTH>
        <PRECISION>0</PRECISION>
        <SCALE>0</SCALE>
    </COLUMN>
    <COLUMN>
        <NAME>CLM_BK_ID</NAME>
        <DEFAULTVALUE/>
        <ALLOWNULL>YES</ALLOWNULL>
        <TYPE>VARCHAR2</TYPE>
        <ID>12</ID>
        <LENGTH>16</LENGTH>
        <PRECISION>0</PRECISION>
        <SCALE>0</SCALE>
    </COLUMN>
    <COLUMN>
        <NAME>CLM_BK_ADD3</NAME>
        <DEFAULTVALUE/>
        <ALLOWNULL>YES</ALLOWNULL>
        <TYPE>VARCHAR2</TYPE>
        <ID>12</ID>
        <LENGTH>35</LENGTH>
        <PRECISION>0</PRECISION>
        <SCALE>0</SCALE>
    </COLUMN>
    <COLUMN>
        <NAME>CLM_BK_ADD2</NAME>
        <DEFAULTVALUE/>
        <ALLOWNULL>YES</ALLOWNULL>
        <TYPE>VARCHAR2</TYPE>
        <ID>12</ID>
        <LENGTH>35</LENGTH>
        <PRECISION>0</PRECISION>
        <SCALE>0</SCALE>
    </COLUMN>
    <COLUMN>
        <NAME>CLM_BK_ADD1</NAME>
        <DEFAULTVALUE/>
        <ALLOWNULL>YES</ALLOWNULL>
        <TYPE>VARCHAR2</TYPE>
        <ID>12</ID>
        <LENGTH>35</LENGTH>
        <PRECISION>0</PRECISION>
        <SCALE>0</SCALE>
    </COLUMN>
    <PKEY>
        <PKNAME ID="12">CLM_REF</PKNAME>
    </PKEY>
    <FKEY/>
</TABLESTRUCTURE>