<?xml version="1.0" encoding="UTF-8"?>
<TABLESTRUCTURE DATABASE="EEPDB" EETYPE="" TABLE="STD_CURRENCY_HIST" ISView="N" Module="">
    <COLUMN>
        <NAME>C_LOCKED_FLAG</NAME>
        <DEFAULTVALUE/>
        <ALLOWNULL>YES</ALLOWNULL>
        <TYPE>VARCHAR2</TYPE>
        <ID>12</ID>
        <LENGTH>1</LENGTH>
        <PRECISION>0</PRECISION>
        <SCALE>0</SCALE>
    </COLUMN>
    <COLUMN>
        <NAME>T_LAST_MODIFY_TIME</NAME>
        <DEFAULTVALUE/>
        <ALLOWNULL>YES</ALLOWNULL>
        <TYPE>TIMESTAMP(6)</TYPE>
        <ID>93</ID>
        <LENGTH>11</LENGTH>
        <PRECISION>0</PRECISION>
        <SCALE>6</SCALE>
    </COLUMN>
    <COLUMN>
        <NAME>C_TRX_STATUS</NAME>
        <DEFAULTVALUE/>
        <ALLOWNULL>YES</ALLOWNULL>
        <TYPE>VARCHAR2</TYPE>
        <ID>12</ID>
        <LENGTH>1</LENGTH>
        <PRECISION>0</PRECISION>
        <SCALE>0</SCALE>
    </COLUMN>
    <COLUMN>
        <NAME>C_ADD_FLAG</NAME>
        <DEFAULTVALUE>'T'</DEFAULTVALUE>
        <ALLOWNULL>YES</ALLOWNULL>
        <TYPE>VARCHAR2</TYPE>
        <ID>12</ID>
        <LENGTH>1</LENGTH>
        <PRECISION>0</PRECISION>
        <SCALE>0</SCALE>
    </COLUMN>
    <COLUMN>
        <NAME>C_RELE_BY</NAME>
        <DEFAULTVALUE/>
        <ALLOWNULL>YES</ALLOWNULL>
        <TYPE>VARCHAR2</TYPE>
        <ID>12</ID>
        <LENGTH>32</LENGTH>
        <PRECISION>0</PRECISION>
        <SCALE>0</SCALE>
    </COLUMN>
    <COLUMN>
        <NAME>C_CREA_BY</NAME>
        <DEFAULTVALUE/>
        <ALLOWNULL>YES</ALLOWNULL>
        <TYPE>VARCHAR2</TYPE>
        <ID>12</ID>
        <LENGTH>32</LENGTH>
        <PRECISION>0</PRECISION>
        <SCALE>0</SCALE>
    </COLUMN>
    <COLUMN>
        <NAME>T_SYS_REL_TIME</NAME>
        <DEFAULTVALUE/>
        <ALLOWNULL>YES</ALLOWNULL>
        <TYPE>TIMESTAMP(6)</TYPE>
        <ID>93</ID>
        <LENGTH>11</LENGTH>
        <PRECISION>0</PRECISION>
        <SCALE>6</SCALE>
    </COLUMN>
    <COLUMN>
        <NAME>D_SYS_REL_DATE</NAME>
        <DEFAULTVALUE/>
        <ALLOWNULL>YES</ALLOWNULL>
        <TYPE>TIMESTAMP(6)</TYPE>
        <ID>93</ID>
        <LENGTH>11</LENGTH>
        <PRECISION>0</PRECISION>
        <SCALE>6</SCALE>
    </COLUMN>
    <COLUMN>
        <NAME>T_SYS_OP_TIME</NAME>
        <DEFAULTVALUE/>
        <ALLOWNULL>YES</ALLOWNULL>
        <TYPE>TIMESTAMP(6)</TYPE>
        <ID>93</ID>
        <LENGTH>11</LENGTH>
        <PRECISION>0</PRECISION>
        <SCALE>6</SCALE>
    </COLUMN>
    <COLUMN>
        <NAME>D_SYS_OP_DATE</NAME>
        <DEFAULTVALUE/>
        <ALLOWNULL>YES</ALLOWNULL>
        <TYPE>TIMESTAMP(6)</TYPE>
        <ID>93</ID>
        <LENGTH>11</LENGTH>
        <PRECISION>0</PRECISION>
        <SCALE>6</SCALE>
    </COLUMN>
    <COLUMN>
        <NAME>I_EVENT_TIMES</NAME>
        <DEFAULTVALUE/>
        <ALLOWNULL>NO</ALLOWNULL>
        <TYPE>NUMBER</TYPE>
        <ID>2</ID>
        <LENGTH>22</LENGTH>
        <PRECISION>22</PRECISION>
        <SCALE>0</SCALE>
    </COLUMN>
    <COLUMN>
        <NAME>I_ISO_CODE</NAME>
        <DEFAULTVALUE/>
        <ALLOWNULL>YES</ALLOWNULL>
        <TYPE>VARCHAR2</TYPE>
        <ID>12</ID>
        <LENGTH>3</LENGTH>
        <PRECISION>0</PRECISION>
        <SCALE>0</SCALE>
    </COLUMN>
    <COLUMN>
        <NAME>C_CACL_METHOD</NAME>
        <DEFAULTVALUE/>
        <ALLOWNULL>YES</ALLOWNULL>
        <TYPE>VARCHAR2</TYPE>
        <ID>12</ID>
        <LENGTH>1</LENGTH>
        <PRECISION>0</PRECISION>
        <SCALE>0</SCALE>
    </COLUMN>
    <COLUMN>
        <NAME>T_BATCH_TIME</NAME>
        <DEFAULTVALUE/>
        <ALLOWNULL>YES</ALLOWNULL>
        <TYPE>DATE</TYPE>
        <ID>91</ID>
        <LENGTH>7</LENGTH>
        <PRECISION>0</PRECISION>
        <SCALE>0</SCALE>
    </COLUMN>
    <COLUMN>
        <NAME>C_INSTITUTION_CODE</NAME>
        <DEFAULTVALUE/>
        <ALLOWNULL>YES</ALLOWNULL>
        <TYPE>VARCHAR2</TYPE>
        <ID>12</ID>
        <LENGTH>12</LENGTH>
        <PRECISION>0</PRECISION>
        <SCALE>0</SCALE>
    </COLUMN>
    <COLUMN>
        <NAME>C_DECIMAL_PRINT_FLAG</NAME>
        <DEFAULTVALUE/>
        <ALLOWNULL>YES</ALLOWNULL>
        <TYPE>VARCHAR2</TYPE>
        <ID>12</ID>
        <LENGTH>2</LENGTH>
        <PRECISION>0</PRECISION>
        <SCALE>0</SCALE>
    </COLUMN>
    <COLUMN>
        <NAME>C_DATA_SOURCE</NAME>
        <DEFAULTVALUE/>
        <ALLOWNULL>YES</ALLOWNULL>
        <TYPE>VARCHAR2</TYPE>
        <ID>12</ID>
        <LENGTH>60</LENGTH>
        <PRECISION>0</PRECISION>
        <SCALE>0</SCALE>
    </COLUMN>
    <COLUMN>
        <NAME>C_CLEARING_COUNTRY</NAME>
        <DEFAULTVALUE/>
        <ALLOWNULL>YES</ALLOWNULL>
        <TYPE>VARCHAR2</TYPE>
        <ID>12</ID>
        <LENGTH>2</LENGTH>
        <PRECISION>0</PRECISION>
        <SCALE>0</SCALE>
    </COLUMN>
    <COLUMN>
        <NAME>I_ORDER_PRIORITY</NAME>
        <DEFAULTVALUE>1</DEFAULTVALUE>
        <ALLOWNULL>YES</ALLOWNULL>
        <TYPE>NUMBER</TYPE>
        <ID>2</ID>
        <LENGTH>22</LENGTH>
        <PRECISION>0</PRECISION>
        <SCALE>0</SCALE>
    </COLUMN>
    <COLUMN>
        <NAME>C_CCY_DESC</NAME>
        <DEFAULTVALUE/>
        <ALLOWNULL>YES</ALLOWNULL>
        <TYPE>VARCHAR2</TYPE>
        <ID>12</ID>
        <LENGTH>70</LENGTH>
        <PRECISION>0</PRECISION>
        <SCALE>0</SCALE>
    </COLUMN>
    <COLUMN>
        <NAME>C_CP_UNIT_CODE</NAME>
        <DEFAULTVALUE/>
        <ALLOWNULL>YES</ALLOWNULL>
        <TYPE>VARCHAR2</TYPE>
        <ID>12</ID>
        <LENGTH>12</LENGTH>
        <PRECISION>0</PRECISION>
        <SCALE>0</SCALE>
    </COLUMN>
    <COLUMN>
        <NAME>I_RATE_DECIMAL</NAME>
        <DEFAULTVALUE/>
        <ALLOWNULL>YES</ALLOWNULL>
        <TYPE>NUMBER</TYPE>
        <ID>2</ID>
        <LENGTH>22</LENGTH>
        <PRECISION>0</PRECISION>
        <SCALE>0</SCALE>
    </COLUMN>
    <COLUMN>
        <NAME>GL_CODE</NAME>
        <DEFAULTVALUE/>
        <ALLOWNULL>YES</ALLOWNULL>
        <TYPE>VARCHAR2</TYPE>
        <ID>12</ID>
        <LENGTH>2</LENGTH>
        <PRECISION>0</PRECISION>
        <SCALE>0</SCALE>
    </COLUMN>
    <COLUMN>
        <NAME>I_BASE_DAY</NAME>
        <DEFAULTVALUE/>
        <ALLOWNULL>YES</ALLOWNULL>
        <TYPE>NUMBER</TYPE>
        <ID>2</ID>
        <LENGTH>22</LENGTH>
        <PRECISION>0</PRECISION>
        <SCALE>0</SCALE>
    </COLUMN>
    <COLUMN>
        <NAME>I_DECIMAL</NAME>
        <DEFAULTVALUE/>
        <ALLOWNULL>YES</ALLOWNULL>
        <TYPE>NUMBER</TYPE>
        <ID>2</ID>
        <LENGTH>22</LENGTH>
        <PRECISION>0</PRECISION>
        <SCALE>0</SCALE>
    </COLUMN>
    <COLUMN>
        <NAME>C_MINOR_NAME</NAME>
        <DEFAULTVALUE/>
        <ALLOWNULL>YES</ALLOWNULL>
        <TYPE>VARCHAR2</TYPE>
        <ID>12</ID>
        <LENGTH>10</LENGTH>
        <PRECISION>0</PRECISION>
        <SCALE>0</SCALE>
    </COLUMN>
    <COLUMN>
        <NAME>C_MAJOR_NAME</NAME>
        <DEFAULTVALUE/>
        <ALLOWNULL>YES</ALLOWNULL>
        <TYPE>VARCHAR2</TYPE>
        <ID>12</ID>
        <LENGTH>50</LENGTH>
        <PRECISION>0</PRECISION>
        <SCALE>0</SCALE>
    </COLUMN>
    <COLUMN>
        <NAME>C_SWIFT_CODE</NAME>
        <DEFAULTVALUE/>
        <ALLOWNULL>YES</ALLOWNULL>
        <TYPE>VARCHAR2</TYPE>
        <ID>12</ID>
        <LENGTH>3</LENGTH>
        <PRECISION>0</PRECISION>
        <SCALE>0</SCALE>
    </COLUMN>
    <COLUMN>
        <NAME>C_COUNTRY</NAME>
        <DEFAULTVALUE/>
        <ALLOWNULL>YES</ALLOWNULL>
        <TYPE>VARCHAR2</TYPE>
        <ID>12</ID>
        <LENGTH>3</LENGTH>
        <PRECISION>0</PRECISION>
        <SCALE>0</SCALE>
    </COLUMN>
    <COLUMN>
        <NAME>C_CURRENCY</NAME>
        <DEFAULTVALUE/>
        <ALLOWNULL>NO</ALLOWNULL>
        <TYPE>VARCHAR2</TYPE>
        <ID>12</ID>
        <LENGTH>3</LENGTH>
        <PRECISION>0</PRECISION>
        <SCALE>0</SCALE>
    </COLUMN>
    <PKEY>
        <PKNAME ID="12">C_CURRENCY</PKNAME>
        <PKNAME ID="2">I_EVENT_TIMES</PKNAME>
    </PKEY>
    <FKEY/>
</TABLESTRUCTURE>