<?xml version="1.0" encoding="UTF-8"?>
<domData>
    <CANCEL_FLG/>
    <CNTY_CODE/>
    <C_MAIN_REF/>
    <C_MAIN_REF_20Z/>
    <MX_OR_MT_FLAG__DESC__/>
    <MX_OR_MT_FLAG/>
    <NXT_STATUS/>
    <PART_50A_ADD_BTN/>
    <SW_FORM/>
    <X102_19_AMT/>
    <X102_19_CCY/>
    <X102_23_BANK_OPERA_CODE/>
    <X102_26T_TRAN_TYPE_CODE/>
    <X102_32A_AMT/>
    <X102_32A_CCY/>
    <X102_32A_DATE/>
    <X102_36_RATE/>
    <X102_50A_ACCOUNT/>
    <X102_50A_IDENTIFIER/>
    <X102_50F_PARTY_ADD1/>
    <X102_50F_PARTY_ADD2/>
    <X102_50F_PARTY_ADD3/>
    <X102_50F_PARTY_ID/>
    <X102_50F_PARTY_NAME/>
    <X102_50_TAG/>
    <X102_51A_IDENTIFIER/>
    <X102_51A_SEND_INS/>
    <X102_52A_IDENTIFIER/>
    <X102_52A_PARTY_IDENTIFIER/>
    <X102_52B_LOCATION/>
    <X102_52_TAG/>
    <X102_53A_IDENTIFIER/>
    <X102_53A_PARTY_IDENTIFIER/>
    <X102_53C_ACCOUNT/>
    <X102_53_TAG/>
    <X102_54A_IDENTIFIER/>
    <X102_54A_PARTY_IDENTIFIER/>
    <X102_71A_CHG_DETAILS/>
    <X102_71G_AMT/>
    <X102_71G_CCY/>
    <X102_72_NARR/>
    <X102_77B_REGULATORY/>
    <X102_SEQ_B>
        <APPL_CNTY_RES/>
        <C_MAIN_REF/>
        <C_UNIT_CODE/>
        <X102_21_REF/>
        <X102_26T_TRAN_TYPE_CODE/>
        <X102_32B_AMT/>
        <X102_32B_CCY/>
        <X102_33B_AMT/>
        <X102_33B_CCY/>
        <X102_36_RATE/>
        <X102_50A_ACCOUNT/>
        <X102_50A_IDENTIFIER/>
        <X102_50F_PARTY_ADD1/>
        <X102_50F_PARTY_ADD2/>
        <X102_50F_PARTY_ADD3/>
        <X102_50F_PARTY_ID/>
        <X102_50F_PARTY_IDENTIFIER/>
        <X102_50F_PARTY_NAME/>
        <X102_50_TAG/>
        <X102_52A_IDENTIFIER/>
        <X102_52A_PARTY_IDENTIFIER/>
        <X102_52B_LOCATION/>
        <X102_52_TAG/>
        <X102_57A_ACC_WITH_IDENTIFIER/>
        <X102_57A_IDENTIFIER/>
        <X102_57_TAG/>
        <X102_59A_ACCOUNT/>
        <X102_59A_IDENTIFIER/>
        <X102_59_PARTY_ADD1/>
        <X102_59_PARTY_ADD2/>
        <X102_59_PARTY_ADD3/>
        <X102_59_PARTY_NAME/>
        <X102_59_TAG/>
        <X102_71A_CHG_DETAILS/>
        <X102_71G_AMT/>
        <X102_71G_CCY/>
        <X102_77B_REGULATORY/>
        <X102_REMITTANCE_INFO/>
        <X103_ADV_BKSW_B2/>
        <X103_ORDCUACNO_50F/>
        <X103_ORDCUADD1_50F/>
        <X103_ORDCUADD2_50F/>
        <X103_ORDCUADD3_50F/>
        <X103_ORDCU_NM_50F/>
        <X102_SEQ_B_71F>
            <X102_71F_CCY/>
            <X102_71F_AMT/>
        </X102_SEQ_B_71F>
    </X102_SEQ_B>
    <X102_SEQ_C_13C>
        <X102_13C_TIME_INDICATION/>
    </X102_SEQ_C_13C>
    <X102_TAG_119/>
    <X103_ADV_BKADD1_B2/>
    <X103_ADV_BKADD2_B2/>
    <X103_ADV_BKADD3_B2/>
    <X103_ADV_BKID_B2/>
    <X103_ADV_BKNM_B2/>
    <X103_ADV_BKSW_B2/>
    <X103_B2_BTN/>
</domData>
