{
  "MT786": {
    "F20": "16x",
    "F21": "16x{0,1}",
    "F23": "16x{0,1}",
    "Choice_52AD": {
      "F52A": {
        "PartyIdentifier": "PTYID'\r\n'{0,1}",
        "IdentifierCode": "BIC"
      },
      "F52D": {
        "PartyIdentifier": "PTYID'\r\n'{0,1}",
        "NameAndAddress": "4*35x"
      }
    },
    "F30": "YYMMDD",
    "F32B": {
      "Currency": "3!a",
      "Amount": "15d"
    },
    "F77J": "70*50z",
    "F77B": "3*35x{0,1}",
    "F72Z": "6*35z{0,1}",
    "F23X": {
      "Code": "4!c(COUR|EMAL|FACT|FAXT|HOST|MAIL|OTHR)'/'",
      "Narrative": "65x",
      "@occur": "{0,1}"
    },
    "@len":10000
  }
}